RuheBianxieJqueryChajian/README.md
RuheBianxieJqueryChajian/__init__.py
RuheBianxieJqueryChajian/__main__.py
RuheBianxieJqueryChajian/file.epub
RuheBianxieJqueryChajian/index.html
RuheBianxieJqueryChajian/css/__init__.py
RuheBianxieJqueryChajian/css/annotations.css
RuheBianxieJqueryChajian/css/main.css
RuheBianxieJqueryChajian/css/normalize.css
RuheBianxieJqueryChajian/css/popup.css
RuheBianxieJqueryChajian/font/__init__.py
RuheBianxieJqueryChajian/font/fontello.eot
RuheBianxieJqueryChajian/font/fontello.svg
RuheBianxieJqueryChajian/font/fontello.ttf
RuheBianxieJqueryChajian/font/fontello.woff
RuheBianxieJqueryChajian/img/__init__.py
RuheBianxieJqueryChajian/img/annotator-glyph-sprite.png
RuheBianxieJqueryChajian/img/annotator-icon-sprite.png
RuheBianxieJqueryChajian/img/apple-touch-icon.png
RuheBianxieJqueryChajian/img/cancelfullscreen.png
RuheBianxieJqueryChajian/img/close.png
RuheBianxieJqueryChajian/img/fullscreen.png
RuheBianxieJqueryChajian/img/loader.gif
RuheBianxieJqueryChajian/img/menu-icon.png
RuheBianxieJqueryChajian/img/save.png
RuheBianxieJqueryChajian/img/saved.png
RuheBianxieJqueryChajian/img/settings-s.png
RuheBianxieJqueryChajian/img/settings.png
RuheBianxieJqueryChajian/img/star.png
RuheBianxieJqueryChajian/js/__init__.py
RuheBianxieJqueryChajian/js/epub.js
RuheBianxieJqueryChajian/js/epub.min.js
RuheBianxieJqueryChajian/js/epub.min.map
RuheBianxieJqueryChajian/js/hooks.min.js
RuheBianxieJqueryChajian/js/hooks.min.map
RuheBianxieJqueryChajian/js/reader.js
RuheBianxieJqueryChajian/js/reader.js.map
RuheBianxieJqueryChajian/js/reader.min.js
RuheBianxieJqueryChajian/js/reader.min.map
RuheBianxieJqueryChajian/js/hooks/__init__.py
RuheBianxieJqueryChajian/js/hooks/extensions/__init__.py
RuheBianxieJqueryChajian/js/hooks/extensions/highlight.js
RuheBianxieJqueryChajian/js/libs/__init__.py
RuheBianxieJqueryChajian/js/libs/jquery.min.js
RuheBianxieJqueryChajian/js/libs/localforage.min.js
RuheBianxieJqueryChajian/js/libs/screenfull.js
ruhe_bianxie_jquery_chajian-2024.3.2.0.dist-info/METADATA
ruhe_bianxie_jquery_chajian-2024.3.2.0.dist-info/WHEEL
ruhe_bianxie_jquery_chajian-2024.3.2.0.dist-info/entry_points.txt
ruhe_bianxie_jquery_chajian-2024.3.2.0.dist-info/top_level.txt
ruhe_bianxie_jquery_chajian-2024.3.2.0.dist-info/RECORD
